spark_sdk/__init__.py
spark_sdk/conf.py
spark_sdk/create_yaml_file.py
spark_sdk/datahub_api.py
spark_sdk/hive_metastore.py
spark_sdk/ingest_hive_datahub.py
spark_sdk/magics.py
spark_sdk/pandas_decrypt.py
spark_sdk/pylineage.py
spark_sdk/pyspark_add_on.py
spark_sdk/utils.py
spark_sdk-0.5.7.dist-info/METADATA
spark_sdk-0.5.7.dist-info/WHEEL
spark_sdk-0.5.7.dist-info/top_level.txt
spark_sdk-0.5.7.dist-info/RECORD
