Metadata-Version: 2.1
Name: spark_sdk
Version: 0.5.7
Summary: Function to help Data Scientist work more effectively with DWH
Home-page: http://git.bigdata.local/data-engineers/sdk/utilities
Author: duyvnc
Author-email: duyvnc@fpt.com.vn
License: duyvnc
Project-URL: Bug Tracker, https://github.com/pypa/sampleproject/issues
Classifier: Programming Language :: Python :: 3
Classifier: License :: OSI Approved :: MIT License
Classifier: Operating System :: OS Independent
Requires-Python: >=3.6
Requires-Dist: pyarrow (<=15.0.0)
Requires-Dist: pycryptodome
Requires-Dist: thrift
Requires-Dist: hmsclient
Requires-Dist: sqlglot
Requires-Dist: findspark
Requires-Dist: acryl-datahub (>=0.10.5.1)
Requires-Dist: pandas (<=1.5.3)
